{
  "$schema": "https://ui.shadcn.com/schema/registry-item.json",
  "name": "theme-dark",
  "type": "registry:theme",
  "files": [],
  "cssVars": {
    "dark": {
      "background": "oklch(from black)",
      "foreground": "oklch(from white)",
      "main": "oklch(from var(--color-mspa-800))",
      "main-foreground": "oklch(from white)",
      "card": "oklch(from var(--color-mspa-900))",
      "card-foreground": "oklch(from white)",
      "popover": "oklch(from black)",
      "popover-foreground": "oklch(from white)",
      "primary": "oklch(from var(--color-sgrub))",
      "primary-foreground": "oklch(from white)",
      "secondary": "oklch(from var(--color-mspa-700))",
      "secondary-foreground": "oklch(from white)",
      "destructive": "oklch(from var(--color-sburb-alpha))",
      "destructive-foreground": "oklch(from white)",
      "muted": "oklch(from var(--color-mspa-700))",
      "muted-foreground": "oklch(from var(--color-mspa-300))",
      "accent": "oklch(from var(--color-mspa-800))",
      "accent-foreground": "oklch(from var(--color-mspa-100))",
      "border": "oklch(from var(--color-mspa-500))",
      "input": "oklch(from var(--color-mspa-500))",
      "ring": "oklch(from var(--color-sgrub))",
      "toast-outline": "oklch(from var(--color-mspa-500))",
      "toast-border": "oklch(from var(--color-mspa-700))"
    }
  }
}